{
    "link": {
        "rel": "self",
        "url": "https://www.sciencebase.gov/catalog/item/5eb4485982ce25b5135abf3c"
    },
    "relatedItems": {
        "link": {
            "url": "https://www.sciencebase.gov/catalog/itemLinks?itemId=5eb4485982ce25b5135abf3c",
            "rel": "related"
        }
    },
    "id": "5eb4485982ce25b5135abf3c",
    "title": "HYDROTHERM - A computer code for simulation of two-phase ground-water flow and heat transport",
    "subTitle": "A computer code for simulation of two-phase ground-water flow and heat transport",
    "summary": "The HYDROTHERM computer program simulates multi-phase ground-water flow and associated thermal energy transport in three dimensions. It can handle high fluid pressures, up to 1 x 109 Pa (104 atm), and high temperatures, up to 1,200 \u00b0C. This report documents the release of Version 3, which includes various additions, modifications, and corrections that have been made to the original simulator. Major changes to the simulator include: 1) the ability to simulate unconfined ground-water flow, 2) a precipitation-recharge boundary condition, 3) a seepage-surface boundary condition at the land surface, 4) the removal of the limitation that a specified-pressure boundary also have a specified temperature, 5) a new iterative solver for the linear [...]",
    "body": "The HYDROTHERM computer program simulates multi-phase ground-water flow and associated thermal energy transport in three dimensions. It can handle high fluid pressures, up to 1 x 109&nbsp;Pa (104&nbsp;atm), and high temperatures, up to 1,200 \u00b0C. This report documents the release of Version 3, which includes various additions, modifications, and corrections that have been made to the original simulator. Major changes to the simulator include: 1) the ability to simulate unconfined ground-water flow, 2) a precipitation-recharge boundary condition, 3) a seepage-surface boundary condition at the land surface, 4) the removal of the limitation that a specified-pressure boundary also have a specified temperature, 5) a new iterative solver for the linear equations based on a generalized minimum-residual method, 6) the ability to use time- or depth-dependent functions for permeability, 7) the conversion of the program code to Fortran 90 to employ dynamic allocation of arrays, and 8) the incorporation of a graphical user interface (GUI) for input and output.",
    "provenance": {
        "dateCreated": "2020-05-07T17:41:45Z",
        "lastUpdated": "2020-09-25T18:53:23Z",
        "lastUpdatedBy": "gdonovan@usgs.gov",
        "createdBy": "sbristol@usgs.gov"
    },
    "hasChildren": false,
    "parentId": "5ed7d36182ce7e579c66e3be",
    "contacts": [
        {
            "name": "Water Resources",
            "oldPartyId": 64247,
            "type": "USGS Mission Area",
            "contactType": "organization",
            "active": true,
            "aliases": [
                "{\"name\":\"USGS Water Resources Mission Area\"}"
            ],
            "organization": {},
            "primaryLocation": {
                "name": "Water Resources Mission Area - Location",
                "streetAddress": {},
                "mailAddress": {}
            }
        },
        {
            "name": "Joshua M Taron",
            "oldPartyId": 60088,
            "type": "Contact",
            "contactType": "person",
            "email": "jmtaron@usgs.gov",
            "active": true,
            "jobTitle": "Research Geophysicist",
            "firstName": "Joshua",
            "middleName": "M",
            "lastName": "Taron",
            "organization": {
                "displayText": "Geology, Minerals, Energy, and Geophysics Science Center"
            },
            "primaryLocation": {
                "name": "Joshua M Taron/GD/USGS/DOI - Primary Location",
                "building": "GSA Bldg 2",
                "buildingCode": "WMB",
                "officePhone": "6503294940",
                "streetAddress": {
                    "line1": "345 Middlefield Road",
                    "city": "Menlo Park",
                    "state": "CA",
                    "zip": "94025"
                },
                "mailAddress": {
                    "line1": "345 Middlefield Road, Mail Stop 973",
                    "mailStopCode": "973",
                    "city": "Menlo Park",
                    "state": "CA",
                    "zip": "94025",
                    "country": "USA"
                }
            }
        }
    ],
    "webLinks": [
        {
            "type": "webLink",
            "typeLabel": "Web Link",
            "uri": "https://volcanoes.usgs.gov/software/hydrotherm/",
            "rel": "related",
            "title": "USGS Webpage",
            "hidden": false
        },
        {
            "typeLabel": "Source Code",
            "uri": "https://volcanoes.usgs.gov/software/hydrotherm/installation.html",
            "title": "Download HYDROTHERM",
            "hidden": false
        },
        {
            "typeLabel": "Web Link",
            "uri": "https://volcanoes.usgs.gov/software/hydrotherm/publications.html",
            "title": "User Documentation",
            "hidden": false
        }
    ],
    "tags": [
        {
            "type": "Subject",
            "name": "Groundwater"
        },
        {
            "type": "Science Topic",
            "name": "Hydrology"
        },
        {
            "type": "Label",
            "name": "Fortran"
        }
    ],
    "files": [
        {
            "cuid": null,
            "key": null,
            "bucket": null,
            "published": null,
            "node": null,
            "name": "hydrotherm.jpg",
            "title": "HYDROTHERM example figure",
            "contentType": "image/jpeg",
            "contentEncoding": null,
            "pathOnDisk": "__disk__78/7b/0c/787b0c5c17a696daad9c87927994b13b169006c0",
            "processed": false,
            "processToken": null,
            "imageWidth": 350,
            "imageHeight": 430,
            "size": 33534,
            "dateUploaded": "2020-06-29T17:00:13Z",
            "uploadedBy": "aliford@usgs.gov",
            "originalMetadata": false,
            "useForPreview": false,
            "s3Object": null,
            "checksum": null,
            "url": "https://www.sciencebase.gov/catalog/file/get/5eb4485982ce25b5135abf3c?f=__disk__78%2F7b%2F0c%2F787b0c5c17a696daad9c87927994b13b169006c0",
            "downloadUri": "https://www.sciencebase.gov/catalog/file/get/5eb4485982ce25b5135abf3c?f=__disk__78%2F7b%2F0c%2F787b0c5c17a696daad9c87927994b13b169006c0",
            "viewUri": "https://www.sciencebase.gov/catalog/file/get/5eb4485982ce25b5135abf3c?f=__disk__78%2F7b%2F0c%2F787b0c5c17a696daad9c87927994b13b169006c0&width=350&height=430",
            "previewImage": {
                "thumbnail": {
                    "uri": "https://www.sciencebase.gov/catalog/file/get/5eb4485982ce25b5135abf3c?f=__disk__78%2F7b%2F0c%2F787b0c5c17a696daad9c87927994b13b169006c0&width=92&height=113",
                    "width": 92,
                    "height": 113
                },
                "small": {
                    "uri": "https://www.sciencebase.gov/catalog/file/get/5eb4485982ce25b5135abf3c?f=__disk__78%2F7b%2F0c%2F787b0c5c17a696daad9c87927994b13b169006c0&width=214&height=263",
                    "width": 214,
                    "height": 263
                }
            }
        }
    ],
    "distributionLinks": [
        {
            "uri": "https://www.sciencebase.gov/catalog/file/get/5eb4485982ce25b5135abf3c",
            "title": "Download Attached Files",
            "type": "downloadLink",
            "typeLabel": "Download Link",
            "rel": "alternate",
            "name": "HYDROTHERM_Acom.zip",
            "files": [
                {
                    "name": "hydrotherm.jpg",
                    "title": "HYDROTHERM example figure",
                    "contentType": "image/jpeg",
                    "size": 33534
                }
            ]
        }
    ],
    "previewImage": {
        "from": "attachedFile",
        "original": {
            "uri": "https://www.sciencebase.gov/catalog/file/get/5eb4485982ce25b5135abf3c?f=__disk__78%2F7b%2F0c%2F787b0c5c17a696daad9c87927994b13b169006c0",
            "viewUri": "https://www.sciencebase.gov/catalog/file/get/5eb4485982ce25b5135abf3c?f=__disk__78%2F7b%2F0c%2F787b0c5c17a696daad9c87927994b13b169006c0&width=350&height=430",
            "viewUrl": "https://www.sciencebase.gov/catalog/file/get/5eb4485982ce25b5135abf3c?deprecated=__use__viewUri__instead__&f=__disk__78%2F7b%2F0c%2F787b0c5c17a696daad9c87927994b13b169006c0&width=350&height=430",
            "width": 350,
            "height": 430,
            "size": 33534,
            "title": "HYDROTHERM example figure"
        },
        "thumbnail": {
            "uri": "https://www.sciencebase.gov/catalog/file/get/5eb4485982ce25b5135abf3c?f=__disk__78%2F7b%2F0c%2F787b0c5c17a696daad9c87927994b13b169006c0&width=92&height=113",
            "width": 92,
            "height": 113
        },
        "small": {
            "uri": "https://www.sciencebase.gov/catalog/file/get/5eb4485982ce25b5135abf3c?f=__disk__78%2F7b%2F0c%2F787b0c5c17a696daad9c87927994b13b169006c0&width=214&height=263",
            "width": 214,
            "height": 263
        }
    }
}